{
  "kind": "singleType",
  "collectionName": "contact_pages",
  "info": {
    "name": "ContactPage",
    "description": ""
  },
  "options": {
    "increments": true,
    "timestamps": true,
    "draftAndPublish": true
  },
  "pluginOptions": {},
  "attributes": {
    "Last_updated": {
      "type": "string"
    },
    "Email": {
      "type": "string"
    },
    "Contact_Number": {
      "type": "string"
    },
    "meta_description": {
      "type": "string"
    },
    "meta_title": {
      "type": "string"
    }
  }
}
